fastapi_project_scaffold-1.0.0.dist-info/licenses/LICENSE
fastapi_scaffold/__init__.py
fastapi_scaffold/__version__.py
fastapi_scaffold/cli/README.md
fastapi_scaffold/cli/__init__.py
fastapi_scaffold/cli/main.py
fastapi_scaffold/cli/requirements.txt
fastapi_scaffold/cli/commands/__init__.py
fastapi_scaffold/cli/commands/check.py
fastapi_scaffold/cli/commands/db.py
fastapi_scaffold/cli/commands/generate.py
fastapi_scaffold/cli/commands/init.py
fastapi_scaffold/cli/templates/README.md
fastapi_scaffold/cli/templates/api.py.j2
fastapi_scaffold/cli/templates/crud.py.j2
fastapi_scaffold/cli/templates/model.py.j2
fastapi_scaffold/cli/templates/schema.py.j2
fastapi_scaffold/cli/utils/__init__.py
fastapi_scaffold/cli/utils/code_gen.py
fastapi_scaffold/cli/utils/file_ops.py
fastapi_scaffold/cli/utils/validators.py
fastapi_scaffold/template/.env.example
fastapi_scaffold/template/.gitignore
fastapi_scaffold/template/README.md
fastapi_scaffold/template/mypy.ini
fastapi_scaffold/template/requirements.txt
fastapi_scaffold/template/app/__init__.py
fastapi_scaffold/template/app/database.py
fastapi_scaffold/template/app/main.py
fastapi_scaffold/template/app/api/__init__.py
fastapi_scaffold/template/app/api/auth.py
fastapi_scaffold/template/app/api/dashboard.py
fastapi_scaffold/template/app/api/dict.py
fastapi_scaffold/template/app/api/enums.py
fastapi_scaffold/template/app/api/examples.py
fastapi_scaffold/template/app/api/permissions.py
fastapi_scaffold/template/app/api/profile.py
fastapi_scaffold/template/app/api/roles.py
fastapi_scaffold/template/app/api/users.py
fastapi_scaffold/template/app/core/__init__.py
fastapi_scaffold/template/app/core/casbin_enforcer.py
fastapi_scaffold/template/app/core/config.py
fastapi_scaffold/template/app/core/dependencies.py
fastapi_scaffold/template/app/core/exceptions.py
fastapi_scaffold/template/app/core/security.py
fastapi_scaffold/template/app/crud/__init__.py
fastapi_scaffold/template/app/crud/dict.py
fastapi_scaffold/template/app/crud/system_config.py
fastapi_scaffold/template/app/models/__init__.py
fastapi_project_scaffold-1.0.0.dist-info/METADATA
fastapi_project_scaffold-1.0.0.dist-info/WHEEL
fastapi_project_scaffold-1.0.0.dist-info/entry_points.txt
fastapi_project_scaffold-1.0.0.dist-info/top_level.txt
fastapi_project_scaffold-1.0.0.dist-info/RECORD
