Metadata-Version: 2.4
Name: fastapi-project-scaffold
Version: 1.0.0
Summary: Enterprise-grade FastAPI project scaffold with CLI and AI-powered code generation
Home-page: https://github.com/btrobot/fastapi-scaffold
Author: Project Team
Author-email: Project Team <support@example.com>
License-Expression: MIT
Project-URL: Homepage, https://github.com/btrobot/fastapi-scaffold
Project-URL: Documentation, https://github.com/btrobot/fastapi-scaffold/blob/main/README.md
Project-URL: Repository, https://github.com/btrobot/fastapi-scaffold
Project-URL: Bug Tracker, https://github.com/btrobot/fastapi-scaffold/issues
Keywords: fastapi,scaffold,cli,code-generator,template,crud,rest-api
Classifier: Development Status :: 4 - Beta
Classifier: Intended Audience :: Developers
Classifier: Topic :: Software Development :: Code Generators
Classifier: Programming Language :: Python :: 3
Classifier: Programming Language :: Python :: 3.10
Classifier: Programming Language :: Python :: 3.11
Classifier: Programming Language :: Python :: 3.12
Classifier: Framework :: FastAPI
Requires-Python: >=3.10
License-File: LICENSE
Requires-Dist: click>=8.1.0
Requires-Dist: jinja2>=3.1.0
Provides-Extra: dev
Requires-Dist: pytest>=7.0.0; extra == "dev"
Requires-Dist: pytest-cov>=4.0.0; extra == "dev"
Requires-Dist: black>=23.0.0; extra == "dev"
Requires-Dist: mypy>=1.0.0; extra == "dev"
Requires-Dist: flake8>=6.0.0; extra == "dev"
Dynamic: author
Dynamic: home-page
Dynamic: license-file
Dynamic: requires-python
